NEMO_fabublox_integration/__init__.py
NEMO_fabublox_integration/admin.py
NEMO_fabublox_integration/app_settings.py
NEMO_fabublox_integration/apps.py
NEMO_fabublox_integration/customization.py
NEMO_fabublox_integration/forms.py
NEMO_fabublox_integration/gcs.py
NEMO_fabublox_integration/models.py
NEMO_fabublox_integration/serializers.py
NEMO_fabublox_integration/synchronize.py
NEMO_fabublox_integration/urls.py
NEMO_fabublox_integration/migrations/0001_initial.py
NEMO_fabublox_integration/migrations/__init__.py
NEMO_fabublox_integration/static/NEMO_fabublox_integration/css/style.css
NEMO_fabublox_integration/templates/NEMO_fabublox_integration/base.html
NEMO_fabublox_integration/templates/NEMO_fabublox_integration/configuration.html
NEMO_fabublox_integration/templates/NEMO_fabublox_integration/in_progress_synchronization.html
NEMO_fabublox_integration/templates/NEMO_fabublox_integration/synchronization.html
NEMO_fabublox_integration/templates/NEMO_fabublox_integration/tools.html
NEMO_fabublox_integration/templates/customizations/customizations_fabublox_integration.html
NEMO_fabublox_integration/tests/__init__.py
NEMO_fabublox_integration/tests/test_fabublox_integration.py
NEMO_fabublox_integration/tests/test_settings.py
NEMO_fabublox_integration/views/__init__.py
NEMO_fabublox_integration/views/fabublox_integration.py
nemo_fabublox_integration-1.0.2.dist-info/licenses/LICENSE
nemo_fabublox_integration-1.0.2.dist-info/METADATA
nemo_fabublox_integration-1.0.2.dist-info/WHEEL
nemo_fabublox_integration-1.0.2.dist-info/top_level.txt
nemo_fabublox_integration-1.0.2.dist-info/RECORD
