Metadata-Version: 2.4
Name: NEMO-fabublox-integration
Version: 1.0.2
Summary: Integration between NEMO and FabuBlox
Author-email: "FabuBlox, Inc." <hello@fabublox.com>
License: MIT License
Project-URL: Homepage, https://gitlab.com/nemo-community/fabublox/nemo-fabublox-integration
Project-URL: Changelog, https://gitlab.com/nemo-community/fabublox/nemo-fabublox-integration/-/releases
Project-URL: Issues, https://gitlab.com/nemo-community/fabublox/nemo-fabublox-integration/-/issues
Project-URL: CI, https://gitlab.com/nemo-community/fabublox/nemo-fabublox-integration/-/pipelines
Keywords: NEMO,FabuBlox
Classifier: Development Status :: 5 - Production/Stable
Classifier: Intended Audience :: Developers
Classifier: License :: OSI Approved :: MIT License
Classifier: Framework :: Django :: 4.2
Classifier: Programming Language :: Python :: 3.9
Classifier: Programming Language :: Python :: 3.10
Classifier: Programming Language :: Python :: 3.11
Classifier: Programming Language :: Python :: 3.12
Classifier: Programming Language :: Python :: 3.13
Requires-Python: >=3.9
License-File: LICENSE
Requires-Dist: django
Requires-Dist: google-cloud-storage<4.0,>=3.2.0
Provides-Extra: nemo-ce
Requires-Dist: NEMO-CE>=6.0.0; extra == "nemo-ce"
Provides-Extra: nemo
Requires-Dist: NEMO>=6.0.0; extra == "nemo"
Provides-Extra: dev-tools
Requires-Dist: pre-commit; extra == "dev-tools"
Requires-Dist: djlint; extra == "dev-tools"
Requires-Dist: black; extra == "dev-tools"
Dynamic: license-file
